setup.py
tornado_subprocess/__init__.py
tornado_subprocess.egg-info/PKG-INFO
tornado_subprocess.egg-info/SOURCES.txt
tornado_subprocess.egg-info/dependency_links.txt
tornado_subprocess.egg-info/not-zip-safe
tornado_subprocess.egg-info/requires.txt
tornado_subprocess.egg-info/top_level.txt